{
    "school": "FIRE",
    "range": 0,
    "learn": {
      "tier": 3
    },
    "cast": {
        "duration": 1,
        "animation": "spell_engine:one_handed_area_charge",
        "sound": {
          "id": "spell_engine:generic_fire_casting",
          "randomness": 0
        },
        "particles": [
          {
            "particle_id": "spell_engine:flame",
            "shape": "PIPE",
            "origin": "FEET",
            "count": 1.0,
            "min_speed": 0.05,
            "max_speed": 0.1
          }
        ]
      },
    "release": {
      "animation": "spell_engine:one_handed_area_release",
      "target": {
        "type": "CLOUD",
        "cloud": {
          "volume": {
            "radius": 4.5,
            "area": {
              "vertical_range_multiplier": 0.3
            },
            "sound": {
              "id": "spell_engine:generic_fire_casting",
              "randomness": 1
            }
          },
          "impact_tick_interval": 15,
          "time_to_live_seconds": 8,
          "client_data": {
            "particles": [
              {
                "particle_id": "lava",
                "shape": "PILLAR",
                "origin": "FEET",
                "count": 2.0,
                "min_speed": 0.0,
                "max_speed": 0.0
              },
              {
                "particle_id": "spell_engine:flame",
                "shape": "PILLAR",
                "origin": "FEET",
                "count": 10.0,
                "min_speed": 0.0,
                "max_speed": 0.0
              },
              {
                "particle_id": "campfire_cosy_smoke",
                "shape": "PILLAR",
                "origin": "FEET",
                "count": 2.0,
                "min_speed": 0.0,
                "max_speed": 0.0
              }
            ]
          }
        }
      }
    },
    "impact": [
      {
        "action": {
            "type": "DAMAGE",
            "damage": {
                "spell_power_coefficient": 0.2
            }
        },
        "particles": [
          {
            "particle_id": "smoke",
            "shape": "SPHERE",
            "origin": "CENTER",
            "count": 10.0,
            "min_speed": 0.1,
            "max_speed": 0.2
          }
        ]
      },
      {
        "action": {
          "type": "FIRE",
          "fire": {
            "duration": 2
          }
        }
      }
    ],
    "cost": {
      "item_id": "runes:fire_stone",
      "exhaust": 0.4,
      "cooldown_duration": 20
    }
  }